{
    "/dist/scripts/main.js": "/dist/scripts/main.js",
    "/dist/styles/main.css": "/dist/styles/main.css",
    "/dist/scripts/common/header-float.js": "/dist/scripts/common/header-float.js",
    "/dist/scripts/common/lazy-loader.js": "/dist/scripts/common/lazy-loader.js",
    "/dist/scripts/common/menu.js": "/dist/scripts/common/menu.js",
    "/dist/scripts/project/reminder.js": "/dist/scripts/project/reminder.js",
    "/dist/scripts/routes/common.js": "/dist/scripts/routes/common.js",
    "/dist/scripts/routes/home.js": "/dist/scripts/routes/home.js",
    "/dist/scripts/routes/project.js": "/dist/scripts/routes/project.js"
}
